{
    "success": true,
    "state": "texas",
    "city": "san antonio",
    "wp_city_post_id": null,
    "locations": [
        {
            "id": "1042",
            "name": "San Antonio",
            "locname": "21750 Hardy Oak Blvd, San Antonio, TX 78258",
            "address": "21750 Hardy Oak Blvd, San Antonio, TX 78258",
            "city": "san antonio",
            "state": "texas",
            "state_english": "Texas",
            "abbr": "TX",
            "phone": "2107391532",
            "premium": "1",
            "opusowned": "0",
            "showpopular": "0",
            "point_x": "29.6450001",
            "point_y": "-98.49166389",
            "url": "/virtual-office/texas/san-antonio/location-1042/",
            "image": {
                "url": "/wp-content-mgr/wp-content/uploads/1042-01-Building.png",
                "alttext": ""
            }
        },
        {
            "id": "1714",
            "name": "San Antonio",
            "locname": "22211 W I-10, San Antonio, TX 78257",
            "address": "22211 W I-10, San Antonio, TX 78257",
            "city": "san antonio",
            "state": "texas",
            "state_english": "Texas",
            "abbr": "TX",
            "phone": "2105389708",
            "premium": "1",
            "opusowned": "0",
            "showpopular": "0",
            "point_x": "29.6558015",
            "point_y": "-98.6255274",
            "url": "/virtual-office/texas/san-antonio/location-1714/",
            "image": {
                "url": "/wp-content-mgr/wp-content/uploads/1714-01.bldg_.jpg",
                "alttext": ""
            }
        },
        {
            "id": "1356",
            "name": "San Antonio",
            "locname": "4040 Broadway Street, San Antonio, TX 78209",
            "address": "4040 Broadway Street, San Antonio, TX 78209",
            "city": "san antonio",
            "state": "texas",
            "state_english": "Texas",
            "abbr": "TX",
            "phone": "2107837031",
            "premium": "1",
            "opusowned": "0",
            "showpopular": "0",
            "point_x": "29.4630539",
            "point_y": "-98.46461320",
            "url": "/virtual-office/texas/san-antonio/location-1356/",
            "image": {
                "url": "/wp-content-mgr/wp-content/uploads/1356-001-Building-e1709840440243.png",
                "alttext": ""
            }
        },
        {
            "id": "880",
            "name": "San Antonio",
            "locname": "5460 Babcock Road, San Antonio, TX 78240",
            "address": "5460 Babcock Road, San Antonio, TX 78240",
            "city": "san antonio",
            "state": "texas",
            "state_english": "Texas",
            "abbr": "TX",
            "phone": "2103383114",
            "premium": "1",
            "opusowned": "0",
            "showpopular": "0",
            "point_x": "29.5167076",
            "point_y": "-98.5948971",
            "url": "/virtual-office/texas/san-antonio/location-880/",
            "image": {
                "url": "/wp-content-mgr/wp-content/uploads/880-001-Building.png",
                "alttext": ""
            }
        }
    ],
    "popular_locations": [],
    "premium_locations": [
        {
            "id": "1042",
            "name": "San Antonio",
            "locname": "21750 Hardy Oak Blvd, San Antonio, TX 78258",
            "address": "21750 Hardy Oak Blvd, San Antonio, TX 78258",
            "city": "san antonio",
            "state": "texas",
            "state_english": "Texas",
            "abbr": "TX",
            "phone": "2107391532",
            "premium": "1",
            "opusowned": "0",
            "showpopular": "0",
            "point_x": "29.6450001",
            "point_y": "-98.49166389",
            "url": "/virtual-office/texas/san-antonio/location-1042/",
            "image": {
                "url": "/wp-content-mgr/wp-content/uploads/1042-01-Building.png",
                "alttext": ""
            }
        },
        {
            "id": "1714",
            "name": "San Antonio",
            "locname": "22211 W I-10, San Antonio, TX 78257",
            "address": "22211 W I-10, San Antonio, TX 78257",
            "city": "san antonio",
            "state": "texas",
            "state_english": "Texas",
            "abbr": "TX",
            "phone": "2105389708",
            "premium": "1",
            "opusowned": "0",
            "showpopular": "0",
            "point_x": "29.6558015",
            "point_y": "-98.6255274",
            "url": "/virtual-office/texas/san-antonio/location-1714/",
            "image": {
                "url": "/wp-content-mgr/wp-content/uploads/1714-01.bldg_.jpg",
                "alttext": ""
            }
        },
        {
            "id": "1356",
            "name": "San Antonio",
            "locname": "4040 Broadway Street, San Antonio, TX 78209",
            "address": "4040 Broadway Street, San Antonio, TX 78209",
            "city": "san antonio",
            "state": "texas",
            "state_english": "Texas",
            "abbr": "TX",
            "phone": "2107837031",
            "premium": "1",
            "opusowned": "0",
            "showpopular": "0",
            "point_x": "29.4630539",
            "point_y": "-98.46461320",
            "url": "/virtual-office/texas/san-antonio/location-1356/",
            "image": {
                "url": "/wp-content-mgr/wp-content/uploads/1356-001-Building-e1709840440243.png",
                "alttext": ""
            }
        },
        {
            "id": "880",
            "name": "San Antonio",
            "locname": "5460 Babcock Road, San Antonio, TX 78240",
            "address": "5460 Babcock Road, San Antonio, TX 78240",
            "city": "san antonio",
            "state": "texas",
            "state_english": "Texas",
            "abbr": "TX",
            "phone": "2103383114",
            "premium": "1",
            "opusowned": "0",
            "showpopular": "0",
            "point_x": "29.5167076",
            "point_y": "-98.5948971",
            "url": "/virtual-office/texas/san-antonio/location-880/",
            "image": {
                "url": "/wp-content-mgr/wp-content/uploads/880-001-Building.png",
                "alttext": ""
            }
        }
    ],
    "regular_locations": [],
    "sections": [
        {
            "title": "OUR SAN ANTONIO\nVIRTUAL OFFICES",
            "body": "<h2></h2>\n<p>Enjoy the benefits of having a business address in San Antonio Texas without the stress and expense surrounding a “traditional office environment”. OpusVO gives you the prestige of having an office with the budget of working from home. Receive all your business mail at a professional office building. No post office box number, just a great business address to use on your business cards and other marketing material.</p>\n<p>You don’t just get a business phone number with your San Antonio virtual office, but also a live receptionist answering your calls the way you want them to be. Stop choosing between capturing new leads for your business and working on current clients. Do both. Get someone who looks out for you while you’re unable to break away.</p>\n",
            "image": {
                "url": "/newsite/wp-content/themes/ThemeDec23/assets/images/califonia-v-office.jpg",
                "alt": "OUR SAN ANTONIO\nVIRTUAL OFFICES",
                "title": "OUR SAN ANTONIO\nVIRTUAL OFFICES"
            },
            "layout": "image_text",
            "imageAlignment": "right"
        },
        {
            "title": "GET A VIRTUAL OFFICE\nIN SAN ANTONIO",
            "body": "<h2></h2>\n<p>Whether you choose to work out of your home or on the road, a San Antonio virtual office will give you the freedom and flexibility to get the job done in the place and style of your choosing. With a local company phone number, live receptionist, premium call transferring, and a professional business address, Opus VO provides a cost-effective way for your company to grow or establish a presence in a new market without any long-term commitments.</p>\n",
            "image": {
                "url": "/newsite/wp-content/themes/ThemeDec23/assets/images/coral-springs.jpg",
                "alt": "GET A VIRTUAL OFFICE\nIN SAN ANTONIO",
                "title": "GET A VIRTUAL OFFICE\nIN SAN ANTONIO"
            },
            "layout": "image_text",
            "imageAlignment": "left"
        }
    ],
    "faqs": [],
    "meta": {
        "locations_count": 4,
        "popular_locations_count": 0,
        "premium_locations_count": 4,
        "regular_locations_count": 0,
        "sections_count": 2,
        "faqs_count": 0
    },
    "seo": {
        "title": "Virtual Office in San Antonio, TX | Multiple Locations Available",
        "meta_description": "Find the ultimate office solution with Opus Virtual Offices in San Antonio, Texas. Our all-inclusive virtual offices cater to your business needs. Sign up today!",
        "canonical": "https://www.opusvirtualoffices.com/virtual-office/texas/san-antonio/",
        "og": {
            "title": "Virtual Office in San Antonio, TX | Multiple Locations Available",
            "description": "Find the ultimate office solution with Opus Virtual Offices in San Antonio, Texas. Our all-inclusive virtual offices cater to your business needs. Sign up today!",
            "url": "https://www.opusvirtualoffices.com/virtual-office/texas/san-antonio/",
            "type": "website",
            "image": "https://www.opusvirtualoffices.com/newsite/wp-content/themes/ThemeDec23/assets/images/opus-logo-main.svg"
        }
    }
}