{
    "success": true,
    "page": "virtual-office/louisiana/marrero",
    "page_type": "location_city",
    "view": "city",
    "seo": {
        "title": "Virtual Office in Marrero, LA | Multiple Locations Available",
        "meta_description": "Find the ultimate office solution with Opus Virtual Offices in Marrero, Louisiana. Our all-inclusive virtual offices cater to your business needs. Sign up today!",
        "canonical": "https://www.opusvirtualoffices.com/virtual-office/louisiana/marrero/",
        "og": {
            "title": "Virtual Office in Marrero, LA | Multiple Locations Available",
            "description": "Find the ultimate office solution with Opus Virtual Offices in Marrero, Louisiana. Our all-inclusive virtual offices cater to your business needs. Sign up today!",
            "url": "https://www.opusvirtualoffices.com/virtual-office/louisiana/marrero/",
            "type": "website",
            "image": "https://www.opusvirtualoffices.com/newsite/wp-content/themes/ThemeDec23/assets/images/opus-logo-main.svg"
        }
    },
    "data": {
        "state": "Louisiana",
        "city": "Marrero",
        "mode": "virtual-office"
    }
}